{
  "$schema": "https://mintlify.com/schema.json",
  "name": "Zaymo Integration",
  "logo": {
    "dark": "/logo/zaymo-dark.svg",
    "light": "/logo/zaymo-light.svg"
  },
  "favicon": "/favicon-32x32.png",
  "colors": {
    "primary": "#7B68EE",
    "light": "#54B8FC",
    "dark": "#7B68EE",
    "anchors": {
      "from": "#7B68EE",
      "to": "#54B8FC"
    }
  },
  "topbarLinks": [
    {
      "name": "Support",
      "url": "mailto:daniel@zaymo.com"
    }
  ],
  "topbarCtaButton": {
    "name": "Login",
    "url": "https://app.zaymo.com"
  },
  "tabs": [
    {
      "name": "API Reference",
      "url": "api-reference"
    }
  ],
  "anchors": [
    
  ],
  "navigation": [
    {
      "group": "Get Started",
      "pages": ["introduction", "usecases"]
    },
    {
      "group": "API Documentation",
      "pages": ["api-reference/introduction"]
    },
    {
      "group": "Product Upsells",
      "pages": [
        "api-reference/upsells/get-products",
        "api-reference/upsells/add-product"
      ]
    }
  ],
  "footerSocials": {
    "twitter": "https://x.com/zaymodotcom",
    "linkedin": "https://www.linkedin.com/company/zaymo"
  }
}
